opm/simulators/BlackOil.cpython-314-x86_64-linux-gnu.so
opm/simulators/GasWater.cpython-314-x86_64-linux-gnu.so
opm/simulators/OnePhase.cpython-314-x86_64-linux-gnu.so
opm/simulators/__init__.py
opm_simulators.libs/libgfortran-83c28eba.so.5.0.0
opm_simulators.libs/libgomp-e985bcbb.so.1.0.0
opm_simulators.libs/libquadmath-2284e583.so.0.0.0
opm_simulators-2025.10.dist-info/METADATA
opm_simulators-2025.10.dist-info/WHEEL
opm_simulators-2025.10.dist-info/top_level.txt
opm_simulators-2025.10.dist-info/RECORD
opm_simulators-2025.10.dist-info/sboms/auditwheel.cdx.json
