Metadata-Version: 2.4
Name: opm-simulators
Version: 2025.10
Summary: OPM-Simulators Python bindings
Home-page: http://www.opm-project.org
Author: The Open Porous Media Project
Author-email: opmuser@gmail.com
License: GPL-3.0-or-later
Classifier: Programming Language :: Python :: 3
Requires-Python: >=3.8
Requires-Dist: six
Requires-Dist: future
Requires-Dist: decorator
Requires-Dist: opm
Requires-Dist: numpy
Dynamic: author
Dynamic: author-email
Dynamic: classifier
Dynamic: description
Dynamic: description-content-type
Dynamic: home-page
Dynamic: license
Dynamic: requires-dist
Dynamic: requires-python
Dynamic: summary
